{
  "readingPassage": "The Industrial Revolution was a period of significant technological, economic, and social change that began in the late 18th century and continued into the 19th century. It marked a transition from agrarian economies based on manual labor and handicrafts to industrial economies characterized by mechanized manufacturing and urbanization.\nOne of the key developments of the Industrial Revolution was the invention and widespread adoption of machinery powered by steam engines. The steam engine, invented by James Watt in the 1760s, revolutionized transportation, manufacturing, and agriculture. It enabled factories to produce goods on a larger scale and at a faster pace, leading to increased productivity and economic growth.\nThe textile industry was one of the first sectors to undergo industrialization. Innovations such as the spinning jenny, water frame, and power loom mechanized the production of textiles, transforming what was once a cottage industry into a factory-based system. Factories emerged in urban centers, drawing rural workers to cities in search of employment.\nThe transportation industry also underwent significant changes during the Industrial Revolution. The construction of canals, roads, and railways facilitated the movement of goods and people across long distances. Steam-powered locomotives revolutionized land transportation, making it faster, more efficient, and less reliant on animal power.\nThe widespread adoption of steam power and machinery had profound effects on society. It led to the growth of urban centers as people migrated from rural areas to seek employment in factories. Urbanization brought about changes in living conditions, social structures, and cultural norms. Factory work often entailed long hours, low wages, and unsafe working conditions, leading to social unrest and labor movements.\nThe Industrial Revolution also had far-reaching consequences for the environment. The burning of fossil fuels, such as coal, to power factories and locomotives resulted in air and water pollution. Deforestation and habitat destruction occurred as industrialization expanded and demand for resources grew. These environmental impacts continue to be felt today, with concerns about climate change and resource depletion.\nDespite its challenges, the Industrial Revolution brought about significant improvements in living standards and technological innovation. It laid the foundation for modern industrial economies and transformed societies around the world. The inventions and advancements of the Industrial Revolution paved the way for further industrialization and globalization in the centuries that followed.\nHowever, the Industrial Revolution also brought about social inequalities and economic disparities. While some individuals and industries prospered, others faced exploitation and hardship. Child labor, poor working conditions, and income inequality were prevalent during this period, prompting calls for social reform and labor rights.\nIn conclusion, the Industrial Revolution was a transformative period in human history, characterized by technological innovation, economic growth, and social change. It revolutionized industries, transportation, and urbanization, shaping the modern world in profound ways. However, it also brought about environmental degradation, social inequality, and labor exploitation, highlighting the complex and multifaceted nature of industrialization.",
  "questions": [
    {
      "question": "When did the Industrial Revolution begin?",
      "options": [
        "15th century",
        "18th century",
        "19th century",
        "20th century"
      ],
      "answer": "18th century"
    },
    {
      "question": "Which invention revolutionized transportation during the Industrial Revolution?",
      "options": [
        "Spinning jenny",
        "Water frame",
        "Power loom",
        "Steam engine"
      ],
      "answer": "Steam engine"
    },
    {
      "question": "What industry was one of the first to undergo industrialization?",
      "options": ["Agriculture", "Textiles", "Mining", "Construction"],
      "answer": "Textiles"
    },
    {
      "question": "What was a consequence of urbanization during the Industrial Revolution?",
      "options": [
        "Decrease in factory production",
        "Increase in rural population",
        "Change in social structures",
        "Expansion of cottage industries"
      ],
      "answer": "Change in social structures"
    },
    {
      "question": "What environmental impact did the Industrial Revolution have?",
      "options": [
        "Increased air and water pollution",
        "Decreased deforestation",
        "Enhanced biodiversity",
        "Reduced habitat destruction"
      ],
      "answer": "Increased air and water pollution"
    },
    {
      "question": "What was a common working condition in factories during the Industrial Revolution?",
      "options": [
        "Short working hours",
        "High wages",
        "Unsafe working conditions",
        "Limited production quotas"
      ],
      "answer": "Unsafe working conditions"
    },
    {
      "question": "What powered most of the machinery during the Industrial Revolution?",
      "options": ["Water", "Electricity", "Steam", "Wind"],
      "answer": "Steam"
    },
    {
      "question": "What was a major consequence of the transportation revolution?",
      "options": [
        "Decreased trade",
        "Isolation of rural areas",
        "Increased urbanization",
        "Expansion of cottage industries"
      ],
      "answer": "Increased urbanization"
    },
    {
      "question": "What social movements emerged in response to working conditions during the Industrial Revolution?",
      "options": [
        "Environmental conservation",
        "Labor rights",
        "Civil rights",
        "Women's suffrage"
      ],
      "answer": "Labor rights"
    },
    {
      "question": "What resource was burned to power factories and locomotives during the Industrial Revolution?",
      "options": ["Coal", "Natural gas", "Solar energy", "Hydropower"],
      "answer": "Coal"
    },
    {
      "question": "What impact did the Industrial Revolution have on living standards?",
      "options": [
        "Decreased living standards",
        "No impact on living standards",
        "Increased living standards",
        "Depends on the region"
      ],
      "answer": "Increased living standards"
    },
    {
      "question": "What characterized the working conditions in factories during the Industrial Revolution?",
      "options": [
        "Short hours and high wages",
        "Safe and healthy environments",
        "Long hours and low wages",
        "Abundant breaks and benefits"
      ],
      "answer": "Long hours and low wages"
    },
    {
      "question": "What economic system emerged during the Industrial Revolution?",
      "options": ["Capitalism", "Communism", "Socialism", "Feudalism"],
      "answer": "Capitalism"
    },
    {
      "question": "What was a significant technological advancement of the Industrial Revolution?",
      "options": ["Internet", "Telegraph", "Television", "Radio"],
      "answer": "Telegraph"
    },
    {
      "question": "What industry was transformed by the inventions of the Industrial Revolution?",
      "options": ["Textiles", "Agriculture", "Mining", "Fishing"],
      "answer": "Textiles"
    },
    {
      "question": "What was a consequence of the rapid urbanization during the Industrial Revolution?",
      "options": [
        "Decrease in social mobility",
        "Increase in literacy rates",
        "Development of suburban areas",
        "Overcrowding and poor sanitation"
      ],
      "answer": "Overcrowding and poor sanitation"
    },
    {
      "question": "What role did coal play in the Industrial Revolution?",
      "options": [
        "It fueled steam engines and factories",
        "It powered wind turbines",
        "It facilitated international trade",
        "It provided clean energy"
      ],
      "answer": "It fueled steam engines and factories"
    },
    {
      "question": "What spurred technological innovation during the Industrial Revolution?",
      "options": [
        "Government regulations",
        "Market demand",
        "Religious beliefs",
        "Social customs"
      ],
      "answer": "Market demand"
    },
    {
      "question": "What was a significant social change during the Industrial Revolution?",
      "options": [
        "Rise of feudalism",
        "Emergence of the middle class",
        "Expansion of serfdom",
        "Decline of urbanization"
      ],
      "answer": "Emergence of the middle class"
    },
    {
      "question": "What contributed to the expansion of global trade during the Industrial Revolution?",
      "options": [
        "Isolationist policies",
        "Technological advancements",
        "Decrease in demand for goods",
        "Limited transportation options"
      ],
      "answer": "Technological advancements"
    }
  ]
}
